helga_prod_fixer.py
setup.py
helga_prod_fixer.egg-info/PKG-INFO
helga_prod_fixer.egg-info/SOURCES.txt
helga_prod_fixer.egg-info/dependency_links.txt
helga_prod_fixer.egg-info/entry_points.txt
helga_prod_fixer.egg-info/top_level.txt