Metadata-Version: 1.1
Name: helga-prod-fixer
Version: 0.3.0
Summary: IRC bot using twisted
Home-page: https://github.com/shaunduncan/helga
Author: Shaun Duncan
Author-email: shaun.duncan@gmail.com
License: MIT
Keywords: helga fix prod
Platform: UNKNOWN
Classifier: Development Status :: 4 - Beta
Classifier: Intended Audience :: Developers
Classifier: License :: OSI Approved :: MIT License
Classifier: Operating System :: OS Independent
Classifier: Programming Language :: Python
Classifier: Topic :: Software Development :: Libraries :: Python Modules
